[{"AddressId":1,"CompanyName":null,"Street":"23 Southridge Point","StreetNumber":"165","PostalCode":null,"City":"Golubac","additionalInfo":null,"UserId":99,"CountryId":54},
{"AddressId":2,"CompanyName":"Ainyx","Street":"759 Dwight Circle","StreetNumber":"91764","PostalCode":"5140-058","City":"Carrazeda de Ansiães","additionalInfo":null,"UserId":181,"CountryId":6},
{"AddressId":3,"CompanyName":null,"Street":"140 Mockingbird Junction","StreetNumber":"7","PostalCode":null,"City":"Tantu","additionalInfo":null,"UserId":110,"CountryId":26},
{"AddressId":4,"CompanyName":"Ozu","Street":"93830 Pierstorff Lane","StreetNumber":"0","PostalCode":"141662","City":"Ramenki","additionalInfo":null,"UserId":58,"CountryId":81},
{"AddressId":5,"CompanyName":"Realpoint","Street":"09159 Commercial Hill","StreetNumber":"9","PostalCode":"80042 CEDEX 1","City":"Amiens","additionalInfo":null,"UserId":185,"CountryId":58},
{"AddressId":6,"CompanyName":null,"Street":"8 Lakewood Gardens Street","StreetNumber":"111","PostalCode":"233009","City":"Pueblo Nuevo","additionalInfo":"Duis bibendum, felis sed interdum venenatis, turpis enim blandit mi, in porttitor pede justo eu massa. Donec dapibus.","UserId":115,"CountryId":61},
{"AddressId":7,"CompanyName":null,"Street":"0 Pearson Terrace","StreetNumber":"6","PostalCode":null,"City":"Burqah","additionalInfo":null,"UserId":177,"CountryId":81},
{"AddressId":8,"CompanyName":null,"Street":"4 La Follette Junction","StreetNumber":"55851","PostalCode":"84019 CEDEX 1","City":"Avignon","additionalInfo":null,"UserId":111,"CountryId":89},
{"AddressId":9,"CompanyName":null,"Street":"176 Cascade Hill","StreetNumber":"47641","PostalCode":null,"City":"Jajaway","additionalInfo":null,"UserId":183,"CountryId":60},
{"AddressId":10,"CompanyName":null,"Street":"4038 Kensington Road","StreetNumber":"2","PostalCode":null,"City":"Barrancas","additionalInfo":null,"UserId":172,"CountryId":54},
{"AddressId":11,"CompanyName":"Zoonder","Street":"9 Laurel Park","StreetNumber":"191","PostalCode":null,"City":"Xuân Trường","additionalInfo":null,"UserId":138,"CountryId":65},
{"AddressId":12,"CompanyName":null,"Street":"73445 Bellgrove Crossing","StreetNumber":"0051","PostalCode":"55188","City":"Saint Paul","additionalInfo":null,"UserId":164,"CountryId":63},
{"AddressId":13,"CompanyName":null,"Street":"67 Hansons Road","StreetNumber":"14","PostalCode":null,"City":"Cinunjang","additionalInfo":null,"UserId":153,"CountryId":68},
{"AddressId":14,"CompanyName":null,"Street":"0 Melby Drive","StreetNumber":"1","PostalCode":"699-4502","City":"Kawagoe","additionalInfo":null,"UserId":182,"CountryId":59},
{"AddressId":15,"CompanyName":"Wikizz","Street":"166 Acker Lane","StreetNumber":"5","PostalCode":null,"City":"Ddmashen","additionalInfo":null,"UserId":43,"CountryId":57},
{"AddressId":16,"CompanyName":null,"Street":"7 Shoshone Center","StreetNumber":"783","PostalCode":null,"City":"Liantan","additionalInfo":null,"UserId":134,"CountryId":40},
{"AddressId":17,"CompanyName":null,"Street":"4358 Tomscot Parkway","StreetNumber":"8558","PostalCode":null,"City":"Shangani","additionalInfo":null,"UserId":166,"CountryId":47},
{"AddressId":18,"CompanyName":null,"Street":"81222 Fremont Terrace","StreetNumber":"45","PostalCode":null,"City":"Tasikmalaya","additionalInfo":null,"UserId":70,"CountryId":66},
{"AddressId":19,"CompanyName":"Oyondu","Street":"4 Miller Trail","StreetNumber":"83442","PostalCode":"396458","City":"Kamensk-Shakhtinskiy","additionalInfo":null,"UserId":153,"CountryId":51},
{"AddressId":20,"CompanyName":"Chatterbridge","Street":"034 Lyons Point","StreetNumber":"45","PostalCode":"64039 CEDEX","City":"Pau","additionalInfo":null,"UserId":42,"CountryId":3},
{"AddressId":21,"CompanyName":null,"Street":"6 Lake View Street","StreetNumber":"29","PostalCode":null,"City":"Tétouan","additionalInfo":null,"UserId":190,"CountryId":75},
{"AddressId":22,"CompanyName":null,"Street":"4 Larry Terrace","StreetNumber":"5802","PostalCode":null,"City":"Jinrui","additionalInfo":null,"UserId":70,"CountryId":93},
{"AddressId":23,"CompanyName":null,"Street":"721 Thackeray Parkway","StreetNumber":"40399","PostalCode":"75080 CEDEX 02","City":"Paris 02","additionalInfo":null,"UserId":19,"CountryId":13},
{"AddressId":24,"CompanyName":"Voonte","Street":"914 Canary Parkway","StreetNumber":"25872","PostalCode":"459 91","City":"Ljungskile","additionalInfo":null,"UserId":155,"CountryId":81},
{"AddressId":25,"CompanyName":null,"Street":"71 Corry Alley","StreetNumber":"1","PostalCode":"860008","City":"Mocoa","additionalInfo":null,"UserId":30,"CountryId":86},
{"AddressId":26,"CompanyName":null,"Street":"8 Ryan Center","StreetNumber":"76755","PostalCode":null,"City":"Zhugentan","additionalInfo":null,"UserId":132,"CountryId":56},
{"AddressId":27,"CompanyName":null,"Street":"1 La Follette Terrace","StreetNumber":"92894","PostalCode":"28055","City":"Madrid","additionalInfo":null,"UserId":190,"CountryId":43},
{"AddressId":28,"CompanyName":null,"Street":"7 Daystar Hill","StreetNumber":"48","PostalCode":"390528","City":"Murmino","additionalInfo":null,"UserId":141,"CountryId":39},
{"AddressId":29,"CompanyName":null,"Street":"2996 Little Fleur Junction","StreetNumber":"55","PostalCode":"18200-000","City":"Itapetininga","additionalInfo":null,"UserId":115,"CountryId":24},
{"AddressId":30,"CompanyName":null,"Street":"24034 Cherokee Alley","StreetNumber":"085","PostalCode":null,"City":"Erdaobaihe","additionalInfo":null,"UserId":3,"CountryId":85},
{"AddressId":31,"CompanyName":"Edgeclub","Street":"31 Moland Terrace","StreetNumber":"8961","PostalCode":null,"City":"Pacobamba","additionalInfo":null,"UserId":47,"CountryId":98},
{"AddressId":32,"CompanyName":"Shuffledrive","Street":"2436 Derek Point","StreetNumber":"2","PostalCode":"739 97","City":"Návsí u Jablunkova","additionalInfo":null,"UserId":165,"CountryId":95},
{"AddressId":33,"CompanyName":"Jaloo","Street":"11 Elka Hill","StreetNumber":"4","PostalCode":"4630","City":"San Roque","additionalInfo":null,"UserId":75,"CountryId":13},
{"AddressId":34,"CompanyName":null,"Street":"9450 Mallard Circle","StreetNumber":"6","PostalCode":null,"City":"Biny Selo","additionalInfo":"Pellentesque viverra pede ac diam. Cras pellentesque volutpat dui.","UserId":149,"CountryId":17},
{"AddressId":35,"CompanyName":null,"Street":"8 Crescent Oaks Road","StreetNumber":"38","PostalCode":"42800-000","City":"Camaçari","additionalInfo":null,"UserId":115,"CountryId":37},
{"AddressId":36,"CompanyName":null,"Street":"77 Crescent Oaks Terrace","StreetNumber":"1","PostalCode":null,"City":"Independencia","additionalInfo":"Nulla facilisi. Cras non velit nec nisi vulputate nonummy.","UserId":91,"CountryId":93},
{"AddressId":37,"CompanyName":null,"Street":"6 Delladonna Drive","StreetNumber":"327","PostalCode":null,"City":"Xinglongchang","additionalInfo":null,"UserId":174,"CountryId":97},
{"AddressId":38,"CompanyName":null,"Street":"4 Grim Road","StreetNumber":"45","PostalCode":"8305","City":"San Agustin","additionalInfo":null,"UserId":46,"CountryId":8},
{"AddressId":39,"CompanyName":null,"Street":"8766 Nelson Court","StreetNumber":"55610","PostalCode":null,"City":"Yangxunqiao","additionalInfo":null,"UserId":99,"CountryId":92},
{"AddressId":40,"CompanyName":null,"Street":"2420 Buell Junction","StreetNumber":"6126","PostalCode":null,"City":"Mt Peto","additionalInfo":null,"UserId":26,"CountryId":84},
{"AddressId":41,"CompanyName":null,"Street":"838 Sunbrook Terrace","StreetNumber":"44759","PostalCode":"1228","City":"Желино","additionalInfo":null,"UserId":156,"CountryId":27},
{"AddressId":42,"CompanyName":null,"Street":"170 Pearson Circle","StreetNumber":"75","PostalCode":null,"City":"Zuogaiduoma","additionalInfo":null,"UserId":33,"CountryId":29},
{"AddressId":43,"CompanyName":null,"Street":"8584 Cambridge Road","StreetNumber":"4611","PostalCode":"8424","City":"Eguia","additionalInfo":null,"UserId":93,"CountryId":16},
{"AddressId":44,"CompanyName":null,"Street":"867 Sauthoff Crossing","StreetNumber":"9726","PostalCode":null,"City":"Jiantou","additionalInfo":null,"UserId":13,"CountryId":94},
{"AddressId":45,"CompanyName":null,"Street":"1 Northfield Place","StreetNumber":"4","PostalCode":null,"City":"Baizhu","additionalInfo":null,"UserId":26,"CountryId":22},
{"AddressId":46,"CompanyName":"Skipfire","Street":"75082 La Follette Alley","StreetNumber":"172","PostalCode":null,"City":"Poli","additionalInfo":null,"UserId":145,"CountryId":91},
{"AddressId":47,"CompanyName":"Oyoba","Street":"135 Del Mar Court","StreetNumber":"7","PostalCode":null,"City":"Alivéri","additionalInfo":null,"UserId":72,"CountryId":63},
{"AddressId":48,"CompanyName":"Vimbo","Street":"0 Emmet Way","StreetNumber":"112","PostalCode":"4335","City":"Angatel","additionalInfo":null,"UserId":69,"CountryId":35},
{"AddressId":49,"CompanyName":"Zoombox","Street":"72852 Westridge Junction","StreetNumber":"8072","PostalCode":"40672","City":"Shah Alam","additionalInfo":null,"UserId":109,"CountryId":12},
{"AddressId":50,"CompanyName":null,"Street":"451 Roth Junction","StreetNumber":"427","PostalCode":"24421","City":"Chakwāl","additionalInfo":null,"UserId":111,"CountryId":18},
{"AddressId":51,"CompanyName":"Realmix","Street":"2615 3rd Crossing","StreetNumber":"28076","PostalCode":null,"City":"Chornobay","additionalInfo":null,"UserId":14,"CountryId":25},
{"AddressId":52,"CompanyName":null,"Street":"16 Sycamore Hill","StreetNumber":"635","PostalCode":"150208","City":"Combita","additionalInfo":null,"UserId":174,"CountryId":86},
{"AddressId":53,"CompanyName":"Vipe","Street":"256 Loeprich Junction","StreetNumber":"904","PostalCode":"190990","City":"Vasyl'evsky Ostrov","additionalInfo":null,"UserId":25,"CountryId":28},
{"AddressId":54,"CompanyName":null,"Street":"71792 Hoepker Circle","StreetNumber":"23","PostalCode":null,"City":"Tanggung","additionalInfo":null,"UserId":148,"CountryId":100},
{"AddressId":55,"CompanyName":"Oodoo","Street":"40774 Shoshone Terrace","StreetNumber":"71099","PostalCode":null,"City":"Takokak","additionalInfo":"Quisque ut erat.","UserId":52,"CountryId":83},
{"AddressId":56,"CompanyName":null,"Street":"5 Brown Alley","StreetNumber":"4","PostalCode":"73130","City":"Phatthalung","additionalInfo":null,"UserId":199,"CountryId":8},
{"AddressId":57,"CompanyName":null,"Street":"27812 Schmedeman Place","StreetNumber":"3","PostalCode":null,"City":"Mugan","additionalInfo":null,"UserId":34,"CountryId":86},
{"AddressId":58,"CompanyName":"Gigashots","Street":"7 Larry Trail","StreetNumber":"59700","PostalCode":"882-0877","City":"Nobeoka","additionalInfo":null,"UserId":143,"CountryId":74},
{"AddressId":59,"CompanyName":null,"Street":"28 Westerfield Junction","StreetNumber":"78","PostalCode":null,"City":"Inkerman","additionalInfo":null,"UserId":146,"CountryId":44},
{"AddressId":60,"CompanyName":"Dynabox","Street":"2664 Melrose Street","StreetNumber":"20","PostalCode":"61635","City":"Peoria","additionalInfo":null,"UserId":148,"CountryId":7},
{"AddressId":61,"CompanyName":"Minyx","Street":"3516 Oak Valley Terrace","StreetNumber":"95530","PostalCode":null,"City":"San José de Barlovento","additionalInfo":null,"UserId":106,"CountryId":3},
{"AddressId":62,"CompanyName":null,"Street":"4 Nancy Plaza","StreetNumber":"486","PostalCode":"8611","City":"Barotac Viejo","additionalInfo":null,"UserId":45,"CountryId":26},
{"AddressId":63,"CompanyName":"Voonte","Street":"050 Bayside Circle","StreetNumber":"9310","PostalCode":"38110","City":"Santa Cruz De Tenerife","additionalInfo":null,"UserId":183,"CountryId":95},
{"AddressId":64,"CompanyName":"Linkbuzz","Street":"133 Eastlawn Drive","StreetNumber":"5788","PostalCode":"V95","City":"Aughrim","additionalInfo":"Integer aliquet, massa id lobortis convallis, tortor risus dapibus augue, vel accumsan tellus nisi eu orci. Mauris lacinia sapien quis libero.","UserId":37,"CountryId":36},
{"AddressId":65,"CompanyName":"Wordtune","Street":"4 Killdeer Court","StreetNumber":"99788","PostalCode":"59425 CEDEX","City":"Armentières","additionalInfo":null,"UserId":173,"CountryId":6},
{"AddressId":66,"CompanyName":null,"Street":"67 Bartillon Plaza","StreetNumber":"65323","PostalCode":"56309 CEDEX","City":"Pontivy","additionalInfo":null,"UserId":174,"CountryId":29},
{"AddressId":67,"CompanyName":null,"Street":"8 Kipling Road","StreetNumber":"4","PostalCode":null,"City":"Trâu Quỳ","additionalInfo":null,"UserId":119,"CountryId":41},
{"AddressId":68,"CompanyName":null,"Street":"8 Scofield Alley","StreetNumber":"7","PostalCode":"5105","City":"Santa Cruz","additionalInfo":"Integer aliquet, massa id lobortis convallis, tortor risus dapibus augue, vel accumsan tellus nisi eu orci.","UserId":164,"CountryId":21},
{"AddressId":69,"CompanyName":"Voonix","Street":"70 Debra Lane","StreetNumber":"0","PostalCode":null,"City":"Kahrīz","additionalInfo":null,"UserId":39,"CountryId":53},
{"AddressId":70,"CompanyName":null,"Street":"377 Sullivan Crossing","StreetNumber":"9","PostalCode":"6271","City":"Italó","additionalInfo":null,"UserId":132,"CountryId":14},
{"AddressId":71,"CompanyName":null,"Street":"8978 Karstens Pass","StreetNumber":"299","PostalCode":null,"City":"Cariamanga","additionalInfo":null,"UserId":42,"CountryId":35},
{"AddressId":72,"CompanyName":null,"Street":"7 Dovetail Plaza","StreetNumber":"235","PostalCode":null,"City":"Cililitan","additionalInfo":null,"UserId":41,"CountryId":8},
{"AddressId":73,"CompanyName":null,"Street":"597 Lindbergh Court","StreetNumber":"6","PostalCode":null,"City":"Tangerang","additionalInfo":null,"UserId":6,"CountryId":72},
{"AddressId":74,"CompanyName":"Meezzy","Street":"9 Loftsgordon Point","StreetNumber":"51832","PostalCode":null,"City":"Lhabupu","additionalInfo":null,"UserId":77,"CountryId":81},
{"AddressId":75,"CompanyName":"Voonix","Street":"213 Milwaukee Alley","StreetNumber":"01248","PostalCode":"3466","City":"Curuzú Cuatiá","additionalInfo":null,"UserId":55,"CountryId":96},
{"AddressId":76,"CompanyName":null,"Street":"265 Little Fleur Terrace","StreetNumber":"6164","PostalCode":"89110-000","City":"Gaspar","additionalInfo":null,"UserId":144,"CountryId":45},
{"AddressId":77,"CompanyName":"Quatz","Street":"9 East Crossing","StreetNumber":"70115","PostalCode":"62400-000","City":"Camocim","additionalInfo":null,"UserId":39,"CountryId":56},
{"AddressId":78,"CompanyName":null,"Street":"7 Kim Street","StreetNumber":"23","PostalCode":"66-470","City":"Kostrzyn nad Odrą","additionalInfo":null,"UserId":150,"CountryId":88},
{"AddressId":79,"CompanyName":null,"Street":"63308 Prentice Parkway","StreetNumber":"312","PostalCode":null,"City":"Zhangqiang","additionalInfo":null,"UserId":135,"CountryId":62},
{"AddressId":80,"CompanyName":null,"Street":"523 Waywood Crossing","StreetNumber":"1","PostalCode":"4525-274","City":"Espinheira","additionalInfo":null,"UserId":168,"CountryId":63},
{"AddressId":81,"CompanyName":"Jabbersphere","Street":"31 Browning Avenue","StreetNumber":"112","PostalCode":"556 31","City":"Jönköping","additionalInfo":"Aenean sit amet justo. Morbi ut odio.","UserId":156,"CountryId":38},
{"AddressId":82,"CompanyName":null,"Street":"056 Dapin Place","StreetNumber":"3961","PostalCode":"623718","City":"Staropyshminsk","additionalInfo":null,"UserId":103,"CountryId":7},
{"AddressId":83,"CompanyName":"Avamm","Street":"392 Debs Junction","StreetNumber":"199","PostalCode":"43226","City":"Višnjevac","additionalInfo":null,"UserId":100,"CountryId":80},
{"AddressId":84,"CompanyName":null,"Street":"64035 Schiller Place","StreetNumber":"37","PostalCode":null,"City":"Shancheng","additionalInfo":null,"UserId":32,"CountryId":51},
{"AddressId":85,"CompanyName":null,"Street":"790 Fairfield Way","StreetNumber":"9","PostalCode":null,"City":"Gostimë","additionalInfo":null,"UserId":107,"CountryId":39},
{"AddressId":86,"CompanyName":null,"Street":"2 Straubel Crossing","StreetNumber":"44347","PostalCode":null,"City":"Andkhōy","additionalInfo":null,"UserId":185,"CountryId":86},
{"AddressId":87,"CompanyName":null,"Street":"2107 Eagan Drive","StreetNumber":"2","PostalCode":null,"City":"Boyany","additionalInfo":null,"UserId":25,"CountryId":1},
{"AddressId":88,"CompanyName":null,"Street":"66978 Sommers Drive","StreetNumber":"45","PostalCode":"6124","City":"Maao","additionalInfo":null,"UserId":178,"CountryId":6},
{"AddressId":89,"CompanyName":"Riffpedia","Street":"3 Sutteridge Way","StreetNumber":"494","PostalCode":null,"City":"Huzhen","additionalInfo":null,"UserId":155,"CountryId":9},
{"AddressId":90,"CompanyName":null,"Street":"92 Starling Alley","StreetNumber":"75172","PostalCode":null,"City":"Sijiqing","additionalInfo":null,"UserId":135,"CountryId":85},
{"AddressId":91,"CompanyName":"Feedbug","Street":"4 Hollow Ridge Terrace","StreetNumber":"78970","PostalCode":null,"City":"Volodymyrets’","additionalInfo":null,"UserId":82,"CountryId":49},
{"AddressId":92,"CompanyName":"Skinder","Street":"2693 Jenifer Drive","StreetNumber":"630","PostalCode":null,"City":"Halong","additionalInfo":null,"UserId":110,"CountryId":37},
{"AddressId":93,"CompanyName":null,"Street":"99 Leroy Parkway","StreetNumber":"75999","PostalCode":null,"City":"Ad Dīs ash Sharqīyah","additionalInfo":null,"UserId":45,"CountryId":59},
{"AddressId":94,"CompanyName":null,"Street":"11 Hoard Center","StreetNumber":"43","PostalCode":null,"City":"Longhe","additionalInfo":"Vestibulum ante ipsum primis in faucibus orci luctus et ultrices posuere cubilia Curae; Duis faucibus accumsan odio. Curabitur convallis.","UserId":99,"CountryId":90},
{"AddressId":95,"CompanyName":"Abatz","Street":"12310 Pepper Wood Terrace","StreetNumber":"45960","PostalCode":null,"City":"Wasior","additionalInfo":null,"UserId":140,"CountryId":92},
{"AddressId":96,"CompanyName":null,"Street":"4430 Rusk Drive","StreetNumber":"297","PostalCode":null,"City":"Funan Chengguanzhen","additionalInfo":null,"UserId":127,"CountryId":84},
{"AddressId":97,"CompanyName":null,"Street":"5365 Harper Way","StreetNumber":"2790","PostalCode":null,"City":"Andou","additionalInfo":null,"UserId":108,"CountryId":17},
{"AddressId":98,"CompanyName":null,"Street":"03685 Hagan Way","StreetNumber":"125","PostalCode":"4770-073","City":"Cabeçudos","additionalInfo":null,"UserId":22,"CountryId":58},
{"AddressId":99,"CompanyName":null,"Street":"18 Drewry Trail","StreetNumber":"790","PostalCode":"659436","City":"Novovladykino","additionalInfo":null,"UserId":65,"CountryId":48},
{"AddressId":100,"CompanyName":null,"Street":"001 Dakota Court","StreetNumber":"31551","PostalCode":null,"City":"Camp Thorel","additionalInfo":null,"UserId":5,"CountryId":14},
{"AddressId":101,"CompanyName":"Oodoo","Street":"75 John Wall Park","StreetNumber":"4","PostalCode":"MD-4006","City":"Maiac","additionalInfo":null,"UserId":91,"CountryId":24},
{"AddressId":102,"CompanyName":null,"Street":"35158 Gateway Drive","StreetNumber":"24780","PostalCode":"2110","City":"Red Hill","additionalInfo":null,"UserId":150,"CountryId":26},
{"AddressId":103,"CompanyName":"Layo","Street":"15 Bunker Hill Way","StreetNumber":"98001","PostalCode":"3332","City":"San Mariano","additionalInfo":null,"UserId":156,"CountryId":34},
{"AddressId":104,"CompanyName":null,"Street":"5 Towne Avenue","StreetNumber":"374","PostalCode":"411 21","City":"Göteborg","additionalInfo":null,"UserId":92,"CountryId":37},
{"AddressId":105,"CompanyName":null,"Street":"58 Moose Lane","StreetNumber":"79","PostalCode":"184653","City":"Polyarnyy","additionalInfo":null,"UserId":141,"CountryId":12},
{"AddressId":106,"CompanyName":null,"Street":"0369 Michigan Trail","StreetNumber":"08494","PostalCode":null,"City":"Mamuša","additionalInfo":null,"UserId":24,"CountryId":3},
{"AddressId":107,"CompanyName":null,"Street":"67232 Del Mar Avenue","StreetNumber":"45","PostalCode":null,"City":"Bến Tre","additionalInfo":null,"UserId":167,"CountryId":19},
{"AddressId":108,"CompanyName":"Eare","Street":"1368 Pennsylvania Place","StreetNumber":"361","PostalCode":"68704 CEDEX","City":"Cernay","additionalInfo":null,"UserId":147,"CountryId":55},
{"AddressId":109,"CompanyName":null,"Street":"1 Talmadge Alley","StreetNumber":"48150","PostalCode":null,"City":"Sayang Lauq","additionalInfo":null,"UserId":78,"CountryId":75},
{"AddressId":110,"CompanyName":"Chatterbridge","Street":"05031 Stuart Pass","StreetNumber":"04812","PostalCode":null,"City":"Liuhao","additionalInfo":null,"UserId":45,"CountryId":73},
{"AddressId":111,"CompanyName":"Camido","Street":"295 Dawn Road","StreetNumber":"0","PostalCode":null,"City":"Balengbeng","additionalInfo":null,"UserId":42,"CountryId":74},
{"AddressId":112,"CompanyName":null,"Street":"38 Maryland Road","StreetNumber":"6422","PostalCode":"618 30","City":"Kolmården","additionalInfo":null,"UserId":102,"CountryId":77},
{"AddressId":113,"CompanyName":"Edgepulse","Street":"12 Glacier Hill Parkway","StreetNumber":"603","PostalCode":"62380-000","City":"Guaraciaba do Norte","additionalInfo":null,"UserId":71,"CountryId":59},
{"AddressId":114,"CompanyName":"Skyble","Street":"33 Coolidge Court","StreetNumber":"83","PostalCode":null,"City":"Cimonyong","additionalInfo":null,"UserId":81,"CountryId":52},
{"AddressId":115,"CompanyName":null,"Street":"9 Carpenter Park","StreetNumber":"31438","PostalCode":null,"City":"Dvorovi","additionalInfo":null,"UserId":128,"CountryId":60},
{"AddressId":116,"CompanyName":null,"Street":"9 Atwood Hill","StreetNumber":"3533","PostalCode":null,"City":"Pumwani","additionalInfo":null,"UserId":166,"CountryId":99},
{"AddressId":117,"CompanyName":null,"Street":"8 Trailsway Place","StreetNumber":"09","PostalCode":null,"City":"Uspenka","additionalInfo":null,"UserId":76,"CountryId":8},
{"AddressId":118,"CompanyName":null,"Street":"4 Green Ridge Place","StreetNumber":"6681","PostalCode":null,"City":"Xiyang","additionalInfo":null,"UserId":3,"CountryId":34},
{"AddressId":119,"CompanyName":null,"Street":"994 Oriole Lane","StreetNumber":"521","PostalCode":null,"City":"Caujul","additionalInfo":null,"UserId":21,"CountryId":33},
{"AddressId":120,"CompanyName":"Blogspan","Street":"6 Katie Pass","StreetNumber":"8","PostalCode":null,"City":"Barang","additionalInfo":null,"UserId":43,"CountryId":64},
{"AddressId":121,"CompanyName":"Devbug","Street":"00844 Roxbury Street","StreetNumber":"2767","PostalCode":null,"City":"Pingyang","additionalInfo":"Nulla ac enim. In tempor, turpis nec euismod scelerisque, quam turpis adipiscing lorem, vitae mattis nibh ligula nec sem.","UserId":185,"CountryId":62},
{"AddressId":122,"CompanyName":"Twitterwire","Street":"5576 Northfield Point","StreetNumber":"9965","PostalCode":null,"City":"Duantan","additionalInfo":null,"UserId":130,"CountryId":79},
{"AddressId":123,"CompanyName":null,"Street":"1427 Barnett Road","StreetNumber":"52936","PostalCode":"111711","City":"Candelaria","additionalInfo":null,"UserId":122,"CountryId":96},
{"AddressId":124,"CompanyName":null,"Street":"35 Fremont Drive","StreetNumber":"42","PostalCode":"14540-000","City":"Igarapava","additionalInfo":null,"UserId":125,"CountryId":16},
{"AddressId":125,"CompanyName":null,"Street":"7 Lakeland Street","StreetNumber":"813","PostalCode":null,"City":"Nanlu","additionalInfo":null,"UserId":44,"CountryId":31},
{"AddressId":126,"CompanyName":null,"Street":"360 Clyde Gallagher Center","StreetNumber":"0","PostalCode":"9512","City":"Dahay","additionalInfo":null,"UserId":91,"CountryId":35},
{"AddressId":127,"CompanyName":null,"Street":"10 Sloan Crossing","StreetNumber":"4911","PostalCode":"4503","City":"Guinobatan","additionalInfo":null,"UserId":102,"CountryId":60},
{"AddressId":128,"CompanyName":null,"Street":"68122 Starling Hill","StreetNumber":"3","PostalCode":null,"City":"Núi Đối","additionalInfo":null,"UserId":173,"CountryId":63},
{"AddressId":129,"CompanyName":null,"Street":"67 Center Place","StreetNumber":"5068","PostalCode":"9318","City":"Balindong","additionalInfo":null,"UserId":189,"CountryId":13},
{"AddressId":130,"CompanyName":null,"Street":"4002 Hanover Alley","StreetNumber":"629","PostalCode":null,"City":"Dubai","additionalInfo":null,"UserId":58,"CountryId":50},
{"AddressId":131,"CompanyName":"Babbleblab","Street":"2931 Rowland Plaza","StreetNumber":"6637","PostalCode":null,"City":"Áno Kopanákion","additionalInfo":null,"UserId":10,"CountryId":93},
{"AddressId":132,"CompanyName":null,"Street":"30082 Glendale Plaza","StreetNumber":"26674","PostalCode":"271 01","City":"Nové Strašecí","additionalInfo":null,"UserId":194,"CountryId":2},
{"AddressId":133,"CompanyName":null,"Street":"28 Carey Center","StreetNumber":"102","PostalCode":null,"City":"Erlangkou","additionalInfo":null,"UserId":70,"CountryId":27},
{"AddressId":134,"CompanyName":null,"Street":"602 American Place","StreetNumber":"66","PostalCode":"TF6","City":"Aston","additionalInfo":null,"UserId":11,"CountryId":33},
{"AddressId":135,"CompanyName":null,"Street":"7 Mayer Junction","StreetNumber":"389","PostalCode":"66-016","City":"Czerwieńsk","additionalInfo":null,"UserId":47,"CountryId":94},
{"AddressId":136,"CompanyName":null,"Street":"596 Fair Oaks Lane","StreetNumber":"2668","PostalCode":"10300","City":"Dusit","additionalInfo":null,"UserId":117,"CountryId":30},
{"AddressId":137,"CompanyName":null,"Street":"41319 Lukken Trail","StreetNumber":"5898","PostalCode":null,"City":"Sarykemer","additionalInfo":null,"UserId":141,"CountryId":45},
{"AddressId":138,"CompanyName":null,"Street":"301 Monument Parkway","StreetNumber":"81","PostalCode":null,"City":"Dalongzhan","additionalInfo":null,"UserId":158,"CountryId":79},
{"AddressId":139,"CompanyName":null,"Street":"00246 Sunnyside Point","StreetNumber":"9","PostalCode":null,"City":"Zhonghuopu","additionalInfo":null,"UserId":19,"CountryId":65},
{"AddressId":140,"CompanyName":null,"Street":"9 Mccormick Junction","StreetNumber":"1461","PostalCode":"8874","City":"Kakamas","additionalInfo":null,"UserId":4,"CountryId":52},
{"AddressId":141,"CompanyName":null,"Street":"0022 Glendale Center","StreetNumber":"3095","PostalCode":"7304","City":"Tipo-Tipo","additionalInfo":null,"UserId":59,"CountryId":55},
{"AddressId":142,"CompanyName":"Skilith","Street":"82425 Doe Crossing Way","StreetNumber":"547","PostalCode":null,"City":"Ampasimanolotra","additionalInfo":null,"UserId":72,"CountryId":38},
{"AddressId":143,"CompanyName":null,"Street":"73 Lunder Road","StreetNumber":"4595","PostalCode":null,"City":"Sukamulya","additionalInfo":null,"UserId":191,"CountryId":39},
{"AddressId":144,"CompanyName":null,"Street":"070 Michigan Crossing","StreetNumber":"4","PostalCode":"4325","City":"Lusacan","additionalInfo":null,"UserId":133,"CountryId":93},
{"AddressId":145,"CompanyName":null,"Street":"0 Basil Road","StreetNumber":"022","PostalCode":null,"City":"Sanlian","additionalInfo":null,"UserId":171,"CountryId":23},
{"AddressId":146,"CompanyName":null,"Street":"84 Morning Hill","StreetNumber":"05","PostalCode":null,"City":"Soba","additionalInfo":null,"UserId":57,"CountryId":45},
{"AddressId":147,"CompanyName":null,"Street":"7 Kennedy Junction","StreetNumber":"2340","PostalCode":null,"City":"Ciherang","additionalInfo":null,"UserId":21,"CountryId":47},
{"AddressId":148,"CompanyName":"Skimia","Street":"8 Pearson Point","StreetNumber":"0325","PostalCode":"127 43","City":"Skärholmen","additionalInfo":null,"UserId":167,"CountryId":68},
{"AddressId":149,"CompanyName":null,"Street":"89 Rowland Alley","StreetNumber":"161","PostalCode":null,"City":"Xibing","additionalInfo":null,"UserId":106,"CountryId":66},
{"AddressId":150,"CompanyName":null,"Street":"2273 Steensland Plaza","StreetNumber":"89","PostalCode":null,"City":"Puunage","additionalInfo":null,"UserId":107,"CountryId":74},
{"AddressId":151,"CompanyName":null,"Street":"6063 Pankratz Park","StreetNumber":"176","PostalCode":null,"City":"Bangeran","additionalInfo":null,"UserId":134,"CountryId":69},
{"AddressId":152,"CompanyName":"Oyoyo","Street":"45 Heffernan Hill","StreetNumber":"1794","PostalCode":null,"City":"Timbulsari","additionalInfo":null,"UserId":40,"CountryId":72},
{"AddressId":153,"CompanyName":null,"Street":"1 Comanche Road","StreetNumber":"566","PostalCode":null,"City":"Tubuhue","additionalInfo":null,"UserId":173,"CountryId":9},
{"AddressId":154,"CompanyName":"Thoughtbridge","Street":"15 Pond Terrace","StreetNumber":"23818","PostalCode":"5602","City":"Libacao","additionalInfo":null,"UserId":149,"CountryId":35},
{"AddressId":155,"CompanyName":null,"Street":"0654 Northview Street","StreetNumber":"8","PostalCode":"391237","City":"Yasenevo","additionalInfo":null,"UserId":72,"CountryId":54},
{"AddressId":156,"CompanyName":"Gabvine","Street":"277 Banding Drive","StreetNumber":"5","PostalCode":null,"City":"Jiaoshi","additionalInfo":null,"UserId":56,"CountryId":99},
{"AddressId":157,"CompanyName":"Realbuzz","Street":"29773 Hoffman Alley","StreetNumber":"61829","PostalCode":"974 42","City":"Luleå","additionalInfo":null,"UserId":147,"CountryId":65},
{"AddressId":158,"CompanyName":null,"Street":"546 Kipling Street","StreetNumber":"5037","PostalCode":"504 67","City":"Borås","additionalInfo":null,"UserId":75,"CountryId":57},
{"AddressId":159,"CompanyName":null,"Street":"589 Johnson Terrace","StreetNumber":"02","PostalCode":null,"City":"Elele","additionalInfo":null,"UserId":171,"CountryId":82},
{"AddressId":160,"CompanyName":null,"Street":"66128 Southridge Alley","StreetNumber":"2504","PostalCode":"49150","City":"Wan Yai","additionalInfo":null,"UserId":120,"CountryId":70},
{"AddressId":161,"CompanyName":null,"Street":"5675 Scofield Crossing","StreetNumber":"04138","PostalCode":null,"City":"Yonghe","additionalInfo":null,"UserId":179,"CountryId":90},
{"AddressId":162,"CompanyName":null,"Street":"05 Browning Park","StreetNumber":"850","PostalCode":"402 57","City":"Göteborg","additionalInfo":null,"UserId":3,"CountryId":46},
{"AddressId":163,"CompanyName":"Kare","Street":"54 Elgar Way","StreetNumber":"60","PostalCode":null,"City":"Caijiagang","additionalInfo":null,"UserId":198,"CountryId":57},
{"AddressId":164,"CompanyName":null,"Street":"78 Petterle Hill","StreetNumber":"34663","PostalCode":null,"City":"Pucallpa","additionalInfo":null,"UserId":199,"CountryId":6},
{"AddressId":165,"CompanyName":null,"Street":"37 Bartillon Crossing","StreetNumber":"60979","PostalCode":null,"City":"Qianyou","additionalInfo":null,"UserId":28,"CountryId":61},
{"AddressId":166,"CompanyName":null,"Street":"8 Sheridan Trail","StreetNumber":"50","PostalCode":"3505-318","City":"Santos Evos","additionalInfo":null,"UserId":73,"CountryId":27},
{"AddressId":167,"CompanyName":null,"Street":"41 Express Court","StreetNumber":"6923","PostalCode":"353508","City":"Temryuk","additionalInfo":null,"UserId":159,"CountryId":15},
{"AddressId":168,"CompanyName":null,"Street":"0230 Delladonna Road","StreetNumber":"6725","PostalCode":"12570-000","City":"Aparecida","additionalInfo":null,"UserId":51,"CountryId":65},
{"AddressId":169,"CompanyName":"Demivee","Street":"00 Florence Terrace","StreetNumber":"2523","PostalCode":"44958 CEDEX 9","City":"Nantes","additionalInfo":null,"UserId":115,"CountryId":66},
{"AddressId":170,"CompanyName":null,"Street":"30 Forster Terrace","StreetNumber":"004","PostalCode":null,"City":"Hexi","additionalInfo":null,"UserId":146,"CountryId":19},
{"AddressId":171,"CompanyName":null,"Street":"4 3rd Drive","StreetNumber":"58397","PostalCode":null,"City":"Dubu","additionalInfo":null,"UserId":77,"CountryId":98},
{"AddressId":172,"CompanyName":"Yadel","Street":"0558 Bay Pass","StreetNumber":"62787","PostalCode":null,"City":"Changfa","additionalInfo":null,"UserId":35,"CountryId":67},
{"AddressId":173,"CompanyName":null,"Street":"5 Oxford Plaza","StreetNumber":"4073","PostalCode":"46852","City":"Fort Wayne","additionalInfo":null,"UserId":133,"CountryId":18},
{"AddressId":174,"CompanyName":null,"Street":"95 Canary Crossing","StreetNumber":"709","PostalCode":null,"City":"Ngembel","additionalInfo":null,"UserId":125,"CountryId":97},
{"AddressId":175,"CompanyName":"Zoomdog","Street":"67 Westridge Street","StreetNumber":"94797","PostalCode":null,"City":"Brengkok","additionalInfo":"Etiam vel augue. Vestibulum rutrum rutrum neque.","UserId":82,"CountryId":81},
{"AddressId":176,"CompanyName":null,"Street":"7677 Browning Court","StreetNumber":"079","PostalCode":"4770-431","City":"Requião","additionalInfo":null,"UserId":94,"CountryId":93},
{"AddressId":177,"CompanyName":"Twitterlist","Street":"8135 Leroy Center","StreetNumber":"230","PostalCode":"87250-000","City":"Peabiru","additionalInfo":null,"UserId":162,"CountryId":49},
{"AddressId":178,"CompanyName":"Blogtags","Street":"39297 Heffernan Street","StreetNumber":"2","PostalCode":null,"City":"Mlanggeng","additionalInfo":null,"UserId":29,"CountryId":62},
{"AddressId":179,"CompanyName":null,"Street":"135 Crowley Point","StreetNumber":"142","PostalCode":"187 14","City":"Täby","additionalInfo":null,"UserId":47,"CountryId":46},
{"AddressId":180,"CompanyName":null,"Street":"8 Waubesa Pass","StreetNumber":"67","PostalCode":"9700-406","City":"Raminho","additionalInfo":null,"UserId":39,"CountryId":1},
{"AddressId":181,"CompanyName":"Agimba","Street":"9512 Reinke Drive","StreetNumber":"3","PostalCode":"96799","City":"Aūa","additionalInfo":null,"UserId":63,"CountryId":96},
{"AddressId":182,"CompanyName":null,"Street":"62 Blue Bill Park Junction","StreetNumber":"1","PostalCode":"662680","City":"Idrinskoye","additionalInfo":null,"UserId":23,"CountryId":26},
{"AddressId":183,"CompanyName":null,"Street":"10087 Oriole Junction","StreetNumber":"07","PostalCode":null,"City":"Trinidad","additionalInfo":null,"UserId":151,"CountryId":78},
{"AddressId":184,"CompanyName":"Meedoo","Street":"43280 Del Sol Court","StreetNumber":"28","PostalCode":"6715","City":"Ashton","additionalInfo":null,"UserId":141,"CountryId":95},
{"AddressId":185,"CompanyName":null,"Street":"3 Basil Point","StreetNumber":"45","PostalCode":"2710-470","City":"São Pedro","additionalInfo":null,"UserId":172,"CountryId":1},
{"AddressId":186,"CompanyName":null,"Street":"8 Scofield Alley","StreetNumber":"45","PostalCode":null,"City":"Jaga","additionalInfo":null,"UserId":2,"CountryId":42},
{"AddressId":187,"CompanyName":null,"Street":"33 Badeau Place","StreetNumber":"899","PostalCode":"19-411","City":"Świętajno","additionalInfo":null,"UserId":186,"CountryId":43},
{"AddressId":188,"CompanyName":null,"Street":"852 Caliangt Place","StreetNumber":"299","PostalCode":null,"City":"Tessalit","additionalInfo":null,"UserId":166,"CountryId":77},
{"AddressId":189,"CompanyName":"Realbuzz","Street":"20111 Walton Pass","StreetNumber":"671","PostalCode":"75374 CEDEX 08","City":"Paris 08","additionalInfo":"Proin eu mi.","UserId":180,"CountryId":58},
{"AddressId":190,"CompanyName":null,"Street":"61953 Linden Place","StreetNumber":"5013","PostalCode":null,"City":"Songon","additionalInfo":null,"UserId":170,"CountryId":74},
{"AddressId":191,"CompanyName":null,"Street":"213 Crownhardt Street","StreetNumber":"608","PostalCode":"309666","City":"Pyatnitskoye","additionalInfo":null,"UserId":99,"CountryId":53},
{"AddressId":192,"CompanyName":"Bubbletube","Street":"6 Dennis Avenue","StreetNumber":"3","PostalCode":"40001","City":"Kupiskis","additionalInfo":null,"UserId":188,"CountryId":37},
{"AddressId":193,"CompanyName":null,"Street":"690 Sycamore Pass","StreetNumber":"0150","PostalCode":null,"City":"Weifang","additionalInfo":"Proin interdum mauris non ligula pellentesque ultrices. Phasellus id sapien in sapien iaculis congue.","UserId":74,"CountryId":90},
{"AddressId":194,"CompanyName":null,"Street":"41933 Namekagon Lane","StreetNumber":"56269","PostalCode":null,"City":"San José de Bocay","additionalInfo":"In hac habitasse platea dictumst.","UserId":132,"CountryId":16},
{"AddressId":195,"CompanyName":null,"Street":"192 Surrey Circle","StreetNumber":"1801","PostalCode":"98280-000","City":"Panambi","additionalInfo":null,"UserId":176,"CountryId":75},
{"AddressId":196,"CompanyName":null,"Street":"6 Mallard Pass","StreetNumber":"64","PostalCode":"18730-000","City":"Itaí","additionalInfo":null,"UserId":24,"CountryId":33},
{"AddressId":197,"CompanyName":null,"Street":"3238 Bunting Terrace","StreetNumber":"83","PostalCode":"1358","City":"Vnanje Gorice","additionalInfo":null,"UserId":189,"CountryId":44},
{"AddressId":198,"CompanyName":null,"Street":"6471 Welch Park","StreetNumber":"87417","PostalCode":null,"City":"Bissorã","additionalInfo":null,"UserId":12,"CountryId":11},
{"AddressId":199,"CompanyName":null,"Street":"5482 Heffernan Court","StreetNumber":"15","PostalCode":"9135-413","City":"Nogueira","additionalInfo":null,"UserId":180,"CountryId":35},
{"AddressId":200,"CompanyName":"Riffpedia","Street":"864 Myrtle Plaza","StreetNumber":"24697","PostalCode":null,"City":"Thành Phố Bà Rịa","additionalInfo":null,"UserId":143,"CountryId":65}]